{"cameraMode":{"drawMode":0,"name":"Shaded","section":"Shading Mode"},"sceneLighting":false,"audioPlay":false,"sceneViewState":{"m_AlwaysRefresh":false,"showFog":true,"showSkybox":false,"showFlares":true,"showImageEffects":true,"showParticleSystems":true,"showVisualEffectGraphs":true,"m_FxEnabled":true},"in2DMode":false,"pivot":{"x":0.7149999737739563,"y":-4.147000312805176,"z":-1.003999948501587},"rotation":{"x":0.2679072320461273,"y":-0.5012364983558655,"z":0.16666091978549958,"w":0.8057370185852051},"size":1.2182210683822632,"orthographic":true}